bulkinvoicer/__init__.py
bulkinvoicer/__main__.py
bulkinvoicer/cli.py
bulkinvoicer/config.py
bulkinvoicer/driver.py
bulkinvoicer/logging-debug.conf
bulkinvoicer/logging.conf
bulkinvoicer/pdf.py
bulkinvoicer/utils.py
bulkinvoicer/fonts/NotoSans-Bold.subset.ttf
bulkinvoicer/fonts/NotoSans-BoldItalic.subset.ttf
bulkinvoicer/fonts/NotoSans-Italic.subset.ttf
bulkinvoicer/fonts/NotoSans-Regular.ttf
bulkinvoicer/fonts/NotoSansMono-Bold.subset.ttf
bulkinvoicer/fonts/NotoSansMono-Regular.subset.ttf
bulkinvoicer/fonts/NotoSerif-Bold.subset.ttf
bulkinvoicer/fonts/NotoSerif-BoldItalic.subset.ttf
bulkinvoicer/fonts/NotoSerif-Italic.subset.ttf
bulkinvoicer/fonts/NotoSerif-Regular.subset.ttf
bulkinvoicer-0.1.2.dist-info/METADATA
bulkinvoicer-0.1.2.dist-info/WHEEL
bulkinvoicer-0.1.2.dist-info/entry_points.txt
bulkinvoicer-0.1.2.dist-info/licenses/LICENSE
bulkinvoicer-0.1.2.dist-info/RECORD
