Metadata-Version: 2.4
Name: bulkinvoicer
Version: 0.1.2
Summary: A simple python script to quickly create bulk invoices.
Project-URL: Homepage, http://github.com/yashovardhan99/bulkinvoicer
Project-URL: Repository, https://github.com/yashovardhan99/bulkinvoicer.git
Project-URL: Changelog, http://github.com/yashovardhan99/bulkinvoicer/blob/master/CHANGELOG.md
Project-URL: Issues, http://github.com/yashovardhan99/bulkinvoicer/issues
Project-URL: funding, https://github.com/yashovardhan99/bulkinvoicer
Project-URL: releasenotes, https://github.com/yashovardhan99/bulkinvoicer/releases
Author-email: Yashovardhan Dhanania <yashovardhandhanania@gmail.com>
Maintainer-email: Yashovardhan Dhanania <yashovardhandhanania@gmail.com>
License-Expression: MIT
License-File: LICENSE
Keywords: bill,finance,invoice,pdf,receipts
Classifier: Development Status :: 2 - Pre-Alpha
Classifier: Environment :: Console
Classifier: Intended Audience :: Developers
Classifier: Intended Audience :: Financial and Insurance Industry
Classifier: Natural Language :: English
Classifier: Operating System :: OS Independent
Classifier: Programming Language :: Python
Classifier: Programming Language :: Python :: 3
Classifier: Programming Language :: Python :: 3.10
Classifier: Programming Language :: Python :: 3.11
Classifier: Programming Language :: Python :: 3.12
Classifier: Programming Language :: Python :: 3.13
Classifier: Topic :: Office/Business :: Financial
Classifier: Typing :: Typed
Requires-Python: >=3.10
Requires-Dist: fpdf2<3.0.0,>=2.8.3
Requires-Dist: polars[calamine]<2.0.0,>=1.29.0
Requires-Dist: pydantic<3.0.0,>=2.11.7
Requires-Dist: qrcode<9.0,>=8.2
Requires-Dist: tomli; python_version < '3.11'
Requires-Dist: tqdm<5.0.0,>=4.67.1
Requires-Dist: uharfbuzz
